.clang-format
.gitignore
CMakeLists.txt
CONTRIBUTING.rst
INSTALL
LICENSE
README
RELEASE_INFO
setup.py
./__init__.py
./fpacking.py
./intpacking.py
./packing.py
./packutil.py
./setup.py
.github/pull_request_template.md
.github/risk_level_guide.md
.github/PULL_REQUEST_TEMPLATE/pull_request_template.md
.github/workflows/pr_checklist.yml
bench/analytics/atlas/charts/Perf.charts
bench/analytics/atlas/charts/README.md
bench/analytics/custom_analysis/.gitignore
bench/analytics/custom_analysis/README.md
bench/analytics/custom_analysis/atlas_analysis.ipynb
bench/analytics/custom_analysis/evergreen_analysis.ipynb
bench/perf_run_py/aggregate_perf_stat.py
bench/perf_run_py/perf_config.py
bench/perf_run_py/perf_json_converter_for_atlas_evergreen.py
bench/perf_run_py/perf_run.py
bench/perf_run_py/perf_stat.py
bench/perf_run_py/perf_stat_collection.py
bench/perf_run_py/validate_expected_stats.py
bench/tiered/CMakeLists.txt
bench/tiered/push_pull.c
bench/workgen/CMakeLists.txt
bench/workgen/latency_metric.py
bench/workgen/validate_mirror_tables.py
bench/workgen/workgen.cpp
bench/workgen/workgen.h
bench/workgen/workgen.i
bench/workgen/workgen_func.c
bench/workgen/workgen_func.h
bench/workgen/workgen_int.h
bench/workgen/workgen_time.h
bench/workgen/wtperf.py
bench/workgen/runner/chunkcache_simple.py
bench/workgen/runner/compress_ratio.py
bench/workgen/runner/evict-btree-hs.py
bench/workgen/runner/example_dynamic_tables.py
bench/workgen/runner/example_prepare.py
bench/workgen/runner/example_prepare_evict_reconcile.py
bench/workgen/runner/example_simple.py
bench/workgen/runner/example_txn.py
bench/workgen/runner/insert_stress.py
bench/workgen/runner/insert_test.py
bench/workgen/runner/maintain_low_dirty_cache.py
bench/workgen/runner/many-dhandle-stress.py
bench/workgen/runner/microbenchmark_prefetch_base.py
bench/workgen/runner/microbenchmark_prefetch_off_verify.py
bench/workgen/runner/microbenchmark_prefetch_on_verify.py
bench/workgen/runner/microbenchmark_rts_fast_truncate.py
test/3rdparty/concurrencytest-0.1.2-locally-modified/concurrencytest.egg-info/PKG-INFO
test/3rdparty/concurrencytest-0.1.2-locally-modified/concurrencytest.egg-info/SOURCES.txt
test/3rdparty/concurrencytest-0.1.2-locally-modified/concurrencytest.egg-info/dependency_links.txt
test/3rdparty/concurrencytest-0.1.2-locally-modified/concurrencytest.egg-info/requires.txt
test/3rdparty/concurrencytest-0.1.2-locally-modified/concurrencytest.egg-info/top_level.txt
test/3rdparty/extras-0.0.3/extras.egg-info/PKG-INFO
test/3rdparty/extras-0.0.3/extras.egg-info/SOURCES.txt
test/3rdparty/extras-0.0.3/extras.egg-info/dependency_links.txt
test/3rdparty/extras-0.0.3/extras.egg-info/top_level.txt
test/3rdparty/python-subunit-1.4.4/python_subunit.egg-info/PKG-INFO
test/3rdparty/python-subunit-1.4.4/python_subunit.egg-info/SOURCES.txt
test/3rdparty/python-subunit-1.4.4/python_subunit.egg-info/dependency_links.txt
test/3rdparty/python-subunit-1.4.4/python_subunit.egg-info/entry_points.txt
test/3rdparty/python-subunit-1.4.4/python_subunit.egg-info/requires.txt
test/3rdparty/python-subunit-1.4.4/python_subunit.egg-info/top_level.txt
test/3rdparty/testscenarios-0.4/lib/testscenarios.egg-info/PKG-INFO
test/3rdparty/testscenarios-0.4/lib/testscenarios.egg-info/SOURCES.txt
test/3rdparty/testscenarios-0.4/lib/testscenarios.egg-info/dependency_links.txt
test/3rdparty/testscenarios-0.4/lib/testscenarios.egg-info/requires.txt
test/3rdparty/testscenarios-0.4/lib/testscenarios.egg-info/top_level.txt
wiredtiger.egg-info/PKG-INFO
wiredtiger.egg-info/SOURCES.txt
wiredtiger.egg-info/dependency_links.txt
wiredtiger.egg-info/requires.txt
wiredtiger.egg-info/top_level.txt