Metadata-Version: 2.1
Name: wiredtiger
Version: 11.3.1
Summary: high performance, scalable, production quality, NoSQL, Open Source extensible platform for data management
Home-page: http://source.wiredtiger.com/
Author: The WiredTiger Development Team, part of MongoDB
Author-email: info@wiredtiger.com
License: GPL2,GPL3,Commercial
Keywords: scalable NoSQL database datastore engine open source
Classifier: Intended Audience :: Developers
Classifier: Programming Language :: C
Classifier: Programming Language :: C++
Classifier: Programming Language :: Python
Classifier: Programming Language :: Java
Classifier: Operating System :: MacOS :: MacOS X
Classifier: Operating System :: POSIX
Classifier: Operating System :: POSIX :: BSD
Classifier: Operating System :: POSIX :: Linux
Classifier: Operating System :: POSIX :: SunOS/Solaris
License-File: LICENSE
Requires-Dist: cmake
Requires-Dist: ninja
